LICENSE
sftputil/__init__.py
sftputil/glob.py
sftputil/sftputil.py
sftputil/sync.py
sftputil-1.2.1.dist-info/LICENSE
sftputil-1.2.1.dist-info/METADATA
sftputil-1.2.1.dist-info/WHEEL
sftputil-1.2.1.dist-info/RECORD
