Metadata-Version: 2.1
Name: sftputil
Version: 1.2.1
Summary: Advanced SFTP functions based on Paramiko
Home-page: https://framagit.org/RomainTT/sftputil
License: Mozilla Public License v2
Keywords: sftp,ssh,sync
Author: Romain TAPREST
Author-email: romain@taprest.fr
Requires-Python: >=3.8,<4.0
Classifier: License :: Other/Proprietary License
Classifier: Programming Language :: Python :: 3
Classifier: Programming Language :: Python :: 3.8
Classifier: Programming Language :: Python :: 3.9
Classifier: Programming Language :: Python :: 3.10
Classifier: Programming Language :: Python :: 3.11
Classifier: Programming Language :: Python :: 3.12
Requires-Dist: paramiko (>=3.3.1,<4.0.0)
Project-URL: Bug Tracker, https://framagit.org/RomainTT/sftputil/-/issues
Project-URL: Repository, https://framagit.org/RomainTT/sftputil
